promptarchitect/__init__.py
promptarchitect/main.py
promptarchitect/prompting.py
promptarchitect/specification.py
promptarchitect/tracing.py
promptarchitect/analysis/__init__.py
promptarchitect/analysis/cli.py
promptarchitect/analysis/core.py
promptarchitect/analysis/psi.py
promptarchitect/analysis/specification.py
promptarchitect/analysis/tests.py
promptarchitect/analysis/prompts/analyze_specification.prompt
promptarchitect/analysis/prompts/analyze_test_cases.prompt
promptarchitect/analysis/prompts/psi_prompt_recommendations.prompt
promptarchitect/completions/__init__.py
promptarchitect/completions/anthropic.py
promptarchitect/completions/azure_openai.py
promptarchitect/completions/core.py
promptarchitect/completions/ollama.py
promptarchitect/completions/openai.py
promptarchitect/provider/anthropic.json
promptarchitect/provider/azure_openai.json
promptarchitect/provider/ollama.json
promptarchitect/provider/openai.json
promptarchitect/reporting/__init__.py
promptarchitect/reporting/core.py
promptarchitect/reporting/html.py
promptarchitect/reporting/json.py
promptarchitect/templates/reports/themes/blue/dashboard.html
promptarchitect/templates/reports/themes/blue/prompt_file.html
promptarchitect/templates/reports/themes/pajamas/dashboard.html
promptarchitect/templates/reports/themes/pajamas/prompt_file.html
promptarchitect/validation/__init__.py
promptarchitect/validation/cli.py
promptarchitect/validation/core.py
promptarchitect/validation/testcases.py
promptarchitect/validation/prompts/question_testcase.prompt
promptarchitect/validation/prompts/score_testcase.prompt
promptarchitect-0.4.3.dist-info/METADATA
promptarchitect-0.4.3.dist-info/WHEEL
promptarchitect-0.4.3.dist-info/entry_points.txt
promptarchitect-0.4.3.dist-info/licenses/LICENSE
promptarchitect-0.4.3.dist-info/RECORD
