Metadata-Version: 2.3
Name: promptarchitect
Version: 0.4.3
Summary: Engineered prompts are carefully designed inputs for AI models to ensure consistent and reliable outputs, playing a crucial role in automated processes involving large language models.
Author-email: Joop Snijder <joop@aigency.com>
License-File: LICENSE
Requires-Python: >=3.11
Requires-Dist: anthropic>=0.32.0
Requires-Dist: azure-identity>=1.18.0
Requires-Dist: bs4>=0.0.2
Requires-Dist: chevron>=0.14.0
Requires-Dist: click>=8.1.3
Requires-Dist: coloredlogs>=15.0.1
Requires-Dist: jinja2>=3.1.4
Requires-Dist: langdetect>=1.0.9
Requires-Dist: markdown>=3.6
Requires-Dist: marko>=2.1.2
Requires-Dist: ollama>=0.3.1
Requires-Dist: openai>=1.37.1
Requires-Dist: opentelemetry-api>=1.27.0
Requires-Dist: opentelemetry-sdk>=1.27.0
Requires-Dist: pydantic>=2.8.2
Requires-Dist: python-dotenv==1.0.1
Requires-Dist: python-frontmatter>=1.0.0
Requires-Dist: retry==0.9.2
Requires-Dist: typer>=0.12.3
